hav/HAV.py
hav/__init__.py
hav/example.py
hav/methods.py
hav/utils.py
hav-0.0.3.dist-info/METADATA
hav-0.0.3.dist-info/WHEEL
hav-0.0.3.dist-info/licenses/LICENSE
hav-0.0.3.dist-info/RECORD
