Metadata-Version: 2.3
Name: hav
Version: 0.0.3
Summary: This HAV (hierarchical ABM validation) package helps you to comprehensively validate agent-based models.
Project-URL: Homepage, https://github.com/AgentLabCn/hav
Project-URL: Bug Tracker, https://github.com/AgentLabCn/hav/issues
Author-email: AgentLabCn <hezhou@ucas.ac.cn>
License-File: LICENSE
Classifier: License :: OSI Approved :: Apache Software License
Classifier: Operating System :: OS Independent
Classifier: Programming Language :: Python :: 3
Requires-Python: >=3.10
Requires-Dist: agentpy>=0.1.5
Requires-Dist: catboost>=1.2.5
Requires-Dist: emcee>=3.1.6
Requires-Dist: matplotlib>=3.7.1
Requires-Dist: numpy>=1.25.2
Requires-Dist: pandas>=1.5.3
Requires-Dist: pgmpy>=0.1.25
Requires-Dist: salib>=1.5.0
Requires-Dist: scipy>=1.14.0
Requires-Dist: statsmodels>=0.14.0
